mcfnmr/__init__.py
mcfnmr/__main__.py
mcfnmr/config.py
mcfnmr/main.py
mcfnmr/core/__init__.py
mcfnmr/core/mcf.py
mcfnmr/demodata/__init__.py
mcfnmr/demodata/bmrb.py
mcfnmr/demodata/download.py
mcfnmr/demodata/loading.py
mcfnmr/demodata/metabominer.py
mcfnmr/demodata/oldbdata.py
mcfnmr/routines/__init__.py
mcfnmr/routines/analysis_plasma_samples.py
mcfnmr/routines/classification.py
mcfnmr/routines/comparison_classification.py
mcfnmr/routines/comparison_quantification.py
mcfnmr/routines/plotting.py
mcfnmr/routines/quantification.py
mcfnmr/routines/scan.py
mcfnmr/routines/test1D.py
mcfnmr/routines/utils.py
mcfnmr/utils/__init__.py
mcfnmr/utils/geometry.py
mcfnmr/utils/loading.py
mcfnmr/utils/parsesvg.py
mcfnmr/utils/plotting.py
mcfnmr/utils/pointspectrum.py
mcfnmr/utils/rasterspectrum.py
mcfnmr/utils/spec2csv.py
mcfnmr/utils/system.py
mcfnmr-0.1.3.dist-info/licenses/AUTHORS
mcfnmr-0.1.3.dist-info/licenses/LICENSE.txt
mcfnmr-0.1.3.dist-info/METADATA
mcfnmr-0.1.3.dist-info/WHEEL
mcfnmr-0.1.3.dist-info/entry_points.txt
mcfnmr-0.1.3.dist-info/top_level.txt
mcfnmr-0.1.3.dist-info/RECORD
