Metadata-Version: 2.4
Name: mcfNMR
Version: 0.1.3
Summary: A Minimum Cost Flow NMR recombinator.
Author: Leonhard Lücken
License-Expression: MIT
Project-URL: Repository, https://github.com/GeoMetabolomics-ICBM/mcfNMR
Project-URL: Issues, https://github.com/GeoMetabolomics-ICBM/mcfNMR/issues
Keywords: NMR,compound identification,mixture reconstruction
Classifier: Development Status :: 3 - Alpha
Classifier: Environment :: Console
Classifier: Topic :: Scientific/Engineering :: Image Processing
Classifier: Topic :: Scientific/Engineering :: Chemistry
Classifier: Programming Language :: Python :: 3
Classifier: Programming Language :: Python :: 3.11
Classifier: Programming Language :: Python :: 3.12
Classifier: Programming Language :: Python :: 3.13
Requires-Python: >=3.11
License-File: LICENSE.txt
License-File: AUTHORS
Requires-Dist: numpy
Requires-Dist: scipy
Requires-Dist: pandas
Requires-Dist: matplotlib
Requires-Dist: seaborn
Requires-Dist: networkx
Requires-Dist: shapely
Requires-Dist: toml
Requires-Dist: svglib
Requires-Dist: reportlab
Requires-Dist: nmrpystar
Requires-Dist: waybackpack
Requires-Dist: wget
Requires-Dist: bs4
Provides-Extra: tests
Requires-Dist: texttest; extra == "tests"
Requires-Dist: pycairo; extra == "tests"
Requires-Dist: PyGObject; extra == "tests"
Provides-Extra: formatter
Requires-Dist: black; extra == "formatter"
Dynamic: license-file
